fledge/__init__.py
fledge/__main__.py
fledge/core.py
fledge/exceptions.py
fledge/frames/__init__.py
fledge/frames/euclidean.py
fledge/generic/__init__.py
fledge/generic/utils.py
fledge/named.py
fledge/projections/__init__.py
fledge/py.typed
fledge/references/__init__.py
fledge/references/homogeneous.py
fledge/references/integers.py
fledge/references/naturals.py
fledge/references/reals.py
fledge/registry.py
fledge/spaces/__init__.py
fledge/spaces/euclidean.py
fledge/transforms/__init__.py
fledge-0.1.0a3.dist-info/entry_points.txt
fledge-0.1.0a3.dist-info/LICENSE.rst
fledge-0.1.0a3.dist-info/WHEEL
fledge-0.1.0a3.dist-info/METADATA
fledge-0.1.0a3.dist-info/RECORD
