Metadata-Version: 2.1
Name: fledge
Version: 0.1.0a3
Summary: Fledge
Home-page: https://github.com/benjamindkilleen/fledge
License: MIT
Author: Benjamin D. Killeen
Author-email: killeen@jhu.edu
Requires-Python: >=3.9,<4
Classifier: Development Status :: 2 - Pre-Alpha
Classifier: License :: OSI Approved :: MIT License
Classifier: Programming Language :: Python :: 3
Classifier: Programming Language :: Python :: 3.9
Requires-Dist: click (>=8.0.1,<9.0.0)
Requires-Dist: networkx (>=2.6.1,<3.0.0)
Requires-Dist: numpy (>=1.21.1,<2.0.0)
Requires-Dist: pyvis (>=0.1.9,<0.2.0)
Project-URL: Changelog, https://github.com/benjamindkilleen/fledge/releases
Project-URL: Documentation, https://fledge.readthedocs.io
Project-URL: Repository, https://github.com/benjamindkilleen/fledge
